jsonfeedvalidator
