Metadata-Version: 1.0
Name: jsonfeedvalidator
Version: 0.0.3
Summary: A JSON feed validator
Home-page: https://github.com/voidfiles/jsonfeedvalidator
Author: Alex Kessinger
Author-email: voidfiles@gmail.com
License: MIT
Platform: UNKNOWN
